four_letter_config/__init__.py
four_letter_config/__main__.py
four_letter_config/cli.py
four_letter_config/file_handler.py
four_letter_config-0.3.0.dist-info/LICENSE
four_letter_config-0.3.0.dist-info/METADATA
four_letter_config-0.3.0.dist-info/WHEEL
four_letter_config-0.3.0.dist-info/entry_points.txt
four_letter_config-0.3.0.dist-info/top_level.txt
four_letter_config-0.3.0.dist-info/RECORD
