Metadata-Version: 2.1
Name: four-letter-config
Version: 0.3.0
Summary: Handle JSON and YAML configuraton files
Home-page: https://gitlab.com/blackstream-x/four-letter-config
Author: Rainer Schwarzbach
Author-email: undisclosed@example.com
License: UNKNOWN
Project-URL: Documentation, https://blackstream-x.gitlab.io/four-letter-config
Project-URL: Source, https://gitlab.com/blackstream-x/four-letter-config
Project-URL: Tracker, https://gitlab.com/blackstream-x/four-letter-config/-/issues
Platform: UNKNOWN
Classifier: Development Status :: 4 - Beta
Classifier: Intended Audience :: Developers
Classifier: Topic :: Software Development :: Libraries
Classifier: License :: OSI Approved :: MIT License
Classifier: Programming Language :: Python :: 3
Classifier: Programming Language :: Python :: 3.6
Classifier: Programming Language :: Python :: 3.7
Classifier: Programming Language :: Python :: 3.8
Classifier: Programming Language :: Python :: 3.9
Classifier: Programming Language :: Python :: 3.10
Classifier: Programming Language :: Python :: 3 :: Only
Requires-Python: >=3.6
License-File: LICENSE
Requires-Dist: PyYAML (>=6.0)
